{
	"__comment": "Designed by AquaCubed with Cubik Studio - https://cubik.studio",
	"textures": {
		"voxels_palette": "items/custom/happy"
	},
	"elements": [ 	 
		{
			"__comment": "Voxels-898483",
			"from": [ 4.3636, 6.303, 3.8788 ],
			"to": [ 4.848448, 6.787848, 12.60607 ],
			"faces": {
				"down": { "uv": [ 4.96, 0.96, 7.04, 3.04 ], "texture": "#voxels_palette" },
				"up": { "uv": [ 4.96, 0.96, 7.04, 3.04 ], "texture": "#voxels_palette" },
				"north": { "uv": [ 4.96, 0.96, 7.04, 3.04 ], "texture": "#voxels_palette" },
				"south": { "uv": [ 4.96, 0.96, 7.04, 3.04 ], "texture": "#voxels_palette" },
				"west": { "uv": [ 4.96, 0.96, 7.04, 3.04 ], "texture": "#voxels_palette" },
				"east": { "uv": [ 4.96, 0.96, 7.04, 3.04 ], "texture": "#voxels_palette" }
			}
		},
		{
			"__comment": "Voxels-FFDE3A",
			"from": [ 4.8485, 1.9394, 3.8788 ],
			"to": [ 12.60608, 3.393945, 4.363648 ],
			"faces": {
				"down": { "uv": [ 8.96, 0.96, 11.04, 3.04 ], "texture": "#voxels_palette" },
				"up": { "uv": [ 8.96, 0.96, 11.04, 3.04 ], "texture": "#voxels_palette" },
				"north": { "uv": [ 8.96, 0.96, 11.04, 3.04 ], "texture": "#voxels_palette" },
				"south": { "uv": [ 8.96, 0.96, 11.04, 3.04 ], "texture": "#voxels_palette" },
				"west": { "uv": [ 8.96, 0.96, 11.04, 3.04 ], "texture": "#voxels_palette" },
				"east": { "uv": [ 8.96, 0.96, 11.04, 3.04 ], "texture": "#voxels_palette" }
			}
		},
		{
			"__comment": "Voxels-FFDE3A",
			"from": [ 4.8485, 3.3939, 3.8788 ],
			"to": [ 7.757591, 3.878748, 4.363648 ],
			"faces": {
				"up": { "uv": [ 8.96, 0.96, 11.04, 3.04 ], "texture": "#voxels_palette" },
				"north": { "uv": [ 8.96, 0.96, 11.04, 3.04 ], "texture": "#voxels_palette" },
				"south": { "uv": [ 8.96, 0.96, 11.04, 3.04 ], "texture": "#voxels_palette" },
				"west": { "uv": [ 8.96, 0.96, 11.04, 3.04 ], "texture": "#voxels_palette" }
			}
		},
		{
			"__comment": "Voxels-FFDE3A",
			"from": [ 4.8485, 3.8788, 3.8788 ],
			"to": [ 6.787894, 9.696981, 4.363648 ],
			"faces": {
				"up": { "uv": [ 8.96, 0.96, 11.04, 3.04 ], "texture": "#voxels_palette" },
				"north": { "uv": [ 8.96, 0.96, 11.04, 3.04 ], "texture": "#voxels_palette" },
				"south": { "uv": [ 8.96, 0.96, 11.04, 3.04 ], "texture": "#voxels_palette" },
				"west": { "uv": [ 8.96, 0.96, 11.04, 3.04 ], "texture": "#voxels_palette" },
				"east": { "uv": [ 8.96, 0.96, 11.04, 3.04 ], "texture": "#voxels_palette" }
			}
		},
		{
			"__comment": "Voxels-898483",
			"from": [ 4.8485, 6.303, 12.1212 ],
			"to": [ 13.09092, 6.787848, 12.60605 ],
			"faces": {
				"down": { "uv": [ 4.96, 0.96, 7.04, 3.04 ], "texture": "#voxels_palette" },
				"up": { "uv": [ 4.96, 0.96, 7.04, 3.04 ], "texture": "#voxels_palette" },
				"north": { "uv": [ 4.96, 0.96, 7.04, 3.04 ], "texture": "#voxels_palette" },
				"south": { "uv": [ 4.96, 0.96, 7.04, 3.04 ], "texture": "#voxels_palette" },
				"east": { "uv": [ 4.96, 0.96, 7.04, 3.04 ], "texture": "#voxels_palette" }
			}
		},
		{
			"__comment": "Voxels-000000",
			"from": [ 6.7879, 3.8788, 3.8788 ],
			"to": [ 10.66669, 4.363648, 4.363648 ],
			"faces": {
				"down": { "uv": [ 12.96, 0.96, 15.04, 3.04 ], "texture": "#voxels_palette" },
				"up": { "uv": [ 12.96, 0.96, 15.04, 3.04 ], "texture": "#voxels_palette" },
				"north": { "uv": [ 12.96, 0.96, 15.04, 3.04 ], "texture": "#voxels_palette" },
				"south": { "uv": [ 12.96, 0.96, 15.04, 3.04 ], "texture": "#voxels_palette" }
			}
		},
		{
			"__comment": "Voxels-000000",
			"from": [ 6.7879, 4.3636, 3.8788 ],
			"to": [ 7.757597, 4.848448, 4.363648 ],
			"faces": {
				"north": { "uv": [ 12.96, 0.96, 15.04, 3.04 ], "texture": "#voxels_palette" },
				"south": { "uv": [ 12.96, 0.96, 15.04, 3.04 ], "texture": "#voxels_palette" }
			}
		},
		{
			"__comment": "Voxels-FFDE3A",
			"from": [ 6.7879, 4.8485, 3.8788 ],
			"to": [ 12.60608, 6.303045, 4.363648 ],
			"faces": {
				"down": { "uv": [ 8.96, 0.96, 11.04, 3.04 ], "texture": "#voxels_palette" },
				"up": { "uv": [ 8.96, 0.96, 11.04, 3.04 ], "texture": "#voxels_palette" },
				"north": { "uv": [ 8.96, 0.96, 11.04, 3.04 ], "texture": "#voxels_palette" },
				"south": { "uv": [ 8.96, 0.96, 11.04, 3.04 ], "texture": "#voxels_palette" },
				"east": { "uv": [ 8.96, 0.96, 11.04, 3.04 ], "texture": "#voxels_palette" }
			}
		},
		{
			"__comment": "Voxels-000000",
			"from": [ 6.7879, 6.303, 3.8788 ],
			"to": [ 7.757597, 8.727242, 4.363648 ],
			"faces": {
				"north": { "uv": [ 12.96, 0.96, 15.04, 3.04 ], "texture": "#voxels_palette" },
				"south": { "uv": [ 12.96, 0.96, 15.04, 3.04 ], "texture": "#voxels_palette" }
			}
		},
		{
			"__comment": "Voxels-FFDE3A",
			"from": [ 6.7879, 8.7273, 3.8788 ],
			"to": [ 12.60608, 9.696997, 4.363648 ],
			"faces": {
				"down": { "uv": [ 8.96, 0.96, 11.04, 3.04 ], "texture": "#voxels_palette" },
				"up": { "uv": [ 8.96, 0.96, 11.04, 3.04 ], "texture": "#voxels_palette" },
				"north": { "uv": [ 8.96, 0.96, 11.04, 3.04 ], "texture": "#voxels_palette" },
				"south": { "uv": [ 8.96, 0.96, 11.04, 3.04 ], "texture": "#voxels_palette" },
				"east": { "uv": [ 8.96, 0.96, 11.04, 3.04 ], "texture": "#voxels_palette" }
			}
		},
		{
			"__comment": "Voxels-000000",
			"from": [ 7.7576, 3.3939, 3.8788 ],
			"to": [ 9.696994, 3.878748, 4.363648 ],
			"faces": {
				"north": { "uv": [ 12.96, 0.96, 15.04, 3.04 ], "texture": "#voxels_palette" },
				"south": { "uv": [ 12.96, 0.96, 15.04, 3.04 ], "texture": "#voxels_palette" }
			}
		},
		{
			"__comment": "Voxels-FFDE3A",
			"from": [ 7.7576, 4.3636, 3.8788 ],
			"to": [ 9.696994, 4.848448, 4.363648 ],
			"faces": {
				"north": { "uv": [ 8.96, 0.96, 11.04, 3.04 ], "texture": "#voxels_palette" },
				"south": { "uv": [ 8.96, 0.96, 11.04, 3.04 ], "texture": "#voxels_palette" }
			}
		},
		{
			"__comment": "Voxels-FFDE3A",
			"from": [ 7.7576, 6.303, 3.8788 ],
			"to": [ 9.696994, 8.727242, 4.363648 ],
			"faces": {
				"north": { "uv": [ 8.96, 0.96, 11.04, 3.04 ], "texture": "#voxels_palette" },
				"south": { "uv": [ 8.96, 0.96, 11.04, 3.04 ], "texture": "#voxels_palette" }
			}
		},
		{
			"__comment": "Voxels-FFDE3A",
			"from": [ 9.697, 3.3939, 3.8788 ],
			"to": [ 12.60609, 3.878748, 4.363648 ],
			"faces": {
				"up": { "uv": [ 8.96, 0.96, 11.04, 3.04 ], "texture": "#voxels_palette" },
				"north": { "uv": [ 8.96, 0.96, 11.04, 3.04 ], "texture": "#voxels_palette" },
				"south": { "uv": [ 8.96, 0.96, 11.04, 3.04 ], "texture": "#voxels_palette" },
				"east": { "uv": [ 8.96, 0.96, 11.04, 3.04 ], "texture": "#voxels_palette" }
			}
		},
		{
			"__comment": "Voxels-000000",
			"from": [ 9.697, 4.3636, 3.8788 ],
			"to": [ 10.6667, 4.848448, 4.363648 ],
			"faces": {
				"north": { "uv": [ 12.96, 0.96, 15.04, 3.04 ], "texture": "#voxels_palette" },
				"south": { "uv": [ 12.96, 0.96, 15.04, 3.04 ], "texture": "#voxels_palette" }
			}
		},
		{
			"__comment": "Voxels-000000",
			"from": [ 9.697, 6.303, 3.8788 ],
			"to": [ 10.6667, 8.727242, 4.363648 ],
			"faces": {
				"north": { "uv": [ 12.96, 0.96, 15.04, 3.04 ], "texture": "#voxels_palette" },
				"south": { "uv": [ 12.96, 0.96, 15.04, 3.04 ], "texture": "#voxels_palette" }
			}
		},
		{
			"__comment": "Voxels-FFDE3A",
			"from": [ 10.6667, 3.8788, 3.8788 ],
			"to": [ 12.60609, 4.848497, 4.363648 ],
			"faces": {
				"north": { "uv": [ 8.96, 0.96, 11.04, 3.04 ], "texture": "#voxels_palette" },
				"south": { "uv": [ 8.96, 0.96, 11.04, 3.04 ], "texture": "#voxels_palette" },
				"west": { "uv": [ 8.96, 0.96, 11.04, 3.04 ], "texture": "#voxels_palette" },
				"east": { "uv": [ 8.96, 0.96, 11.04, 3.04 ], "texture": "#voxels_palette" }
			}
		},
		{
			"__comment": "Voxels-FFDE3A",
			"from": [ 10.6667, 6.303, 3.8788 ],
			"to": [ 12.60609, 8.727242, 4.363648 ],
			"faces": {
				"north": { "uv": [ 8.96, 0.96, 11.04, 3.04 ], "texture": "#voxels_palette" },
				"south": { "uv": [ 8.96, 0.96, 11.04, 3.04 ], "texture": "#voxels_palette" },
				"east": { "uv": [ 8.96, 0.96, 11.04, 3.04 ], "texture": "#voxels_palette" }
			}
		},
		{
			"__comment": "Voxels-898483",
			"from": [ 12.6061, 6.303, 3.8788 ],
			"to": [ 13.09095, 6.787848, 12.12122 ],
			"faces": {
				"down": { "uv": [ 4.96, 0.96, 7.04, 3.04 ], "texture": "#voxels_palette" },
				"up": { "uv": [ 4.96, 0.96, 7.04, 3.04 ], "texture": "#voxels_palette" },
				"north": { "uv": [ 4.96, 0.96, 7.04, 3.04 ], "texture": "#voxels_palette" },
				"west": { "uv": [ 4.96, 0.96, 7.04, 3.04 ], "texture": "#voxels_palette" },
				"east": { "uv": [ 4.96, 0.96, 7.04, 3.04 ], "texture": "#voxels_palette" }
			}
		}
	],
	"display": {
		"thirdperson_righthand": {
			"rotation":  [ 0, 0, 92 ],
			"scale":  [ 0.8, 0.8, 0.8 ]
		},
		"thirdperson_lefthand": {
			"rotation":  [ 0, 0, 92 ],
			"scale":  [ 0.8, 0.8, 0.8 ]
		},
		"firstperson_righthand": {
			"translation":  [ 3.4782, 2.7826, 0 ]
		},
		"firstperson_lefthand": {
			"translation":  [ 3.4782, 2.7826, 0 ]
		},
		"gui": {
			"rotation":  [ 0, 180, 0 ],
			"translation":  [ 0.6956, 1.3913, 0 ]
		},
		"head": {
			"translation":  [ -1.2, 3.7, 0 ],
			"scale":  [ 1.6955, 1.6955, 1.6955 ]
		},
		"ground": {
			"translation":  [ 0, 2.7826, 0 ]
		},
		"fixed": {
			"translation":  [ -1.391, 3.4782, 0 ],
			"scale":  [ 1.4, 1.4, 1.4 ]
		}
	}
}